hg/__init__.py
hg/duplicates.py
hg/fp_tree.py
hg-0.0.7.dist-info/LICENSE
hg-0.0.7.dist-info/METADATA
hg-0.0.7.dist-info/WHEEL
hg-0.0.7.dist-info/top_level.txt
hg-0.0.7.dist-info/RECORD
