Metadata-Version: 2.1
Name: hg
Version: 0.0.7
Summary: Homogenous Groups (Duplication detection, Frequent Itemsets, etc.)
Author: Thor Whalen
License: mit
License-File: LICENSE
